qfluentwidgets/__init__.py
qfluentwidgets/_rc/__init__.py
qfluentwidgets/_rc/i18n/qfluentwidgets.ar_AR.qm
qfluentwidgets/_rc/i18n/qfluentwidgets.ar_AR.ts
qfluentwidgets/_rc/i18n/qfluentwidgets.en_US.qm
qfluentwidgets/_rc/i18n/qfluentwidgets.en_US.ts
qfluentwidgets/_rc/i18n/qfluentwidgets.ru_RU.qm
qfluentwidgets/_rc/i18n/qfluentwidgets.ru_RU.ts
qfluentwidgets/_rc/i18n/qfluentwidgets.zh_CN.qm
qfluentwidgets/_rc/i18n/qfluentwidgets.zh_CN.ts
qfluentwidgets/_rc/i18n/qfluentwidgets.zh_HK.qm
qfluentwidgets/_rc/i18n/qfluentwidgets.zh_HK.ts
qfluentwidgets/_rc/i18n/qfluentwidgets.zh_TW.qm
qfluentwidgets/_rc/i18n/qfluentwidgets.zh_TW.ts
qfluentwidgets/_rc/images/acrylic/noise.png
qfluentwidgets/_rc/images/check_box/Accept_black.svg
qfluentwidgets/_rc/images/check_box/Accept_white.svg
qfluentwidgets/_rc/images/check_box/PartialAccept_black.svg
qfluentwidgets/_rc/images/check_box/PartialAccept_white.svg
qfluentwidgets/_rc/images/color_dialog/Clear_black.svg
qfluentwidgets/_rc/images/color_dialog/Clear_white.svg
qfluentwidgets/_rc/images/color_dialog/HuePanel.png
qfluentwidgets/_rc/images/controls/Acrylic.png
qfluentwidgets/_rc/images/controls/AnimatedIcon.png
qfluentwidgets/_rc/images/controls/AppBarButton.png
qfluentwidgets/_rc/images/controls/AppBarSeparator.png
qfluentwidgets/_rc/images/controls/AppBarToggleButton.png
qfluentwidgets/_rc/images/controls/AutoSuggestBox.png
qfluentwidgets/_rc/images/controls/BreadcrumbBar.png
qfluentwidgets/_rc/images/controls/Button.png
qfluentwidgets/_rc/images/controls/CalendarDatePicker.png
qfluentwidgets/_rc/images/controls/CalendarView.png
qfluentwidgets/_rc/images/controls/Canvas.png
qfluentwidgets/_rc/images/controls/Checkbox.png
qfluentwidgets/_rc/images/controls/Clipboard.png
qfluentwidgets/_rc/images/controls/ColorPaletteResources.png
qfluentwidgets/_rc/images/controls/ColorPicker.png
qfluentwidgets/_rc/images/controls/ComboBox.png
qfluentwidgets/_rc/images/controls/CommandBar.png
Fluent_Widgets_QIAO-0.5.0.dist-info/WHEEL
Fluent_Widgets_QIAO-0.5.0.dist-info/METADATA
Fluent_Widgets_QIAO-0.5.0.dist-info/licenses/LICENSE
Fluent_Widgets_QIAO-0.5.0.dist-info/RECORD
