Metadata-Version: 2.1
Name: Fluent-Widgets-QIAO
Version: 0.5.0
Summary: 基于 PyQt-Fluent-Widgets 的组件库
License: GPLv3
Author-email: Qiao <SugarQiao@outlook.com>
Requires-Python: <3.13, >=3.10
Requires-Dist: PySide6<=6.7.2,>=6.4.2
Requires-Dist: PySideSix-Frameless-Window>=0.4.0
Requires-Dist: colorthief
Requires-Dist: darkdetect
Requires-Dist: pillow
Requires-Dist: scipy
